dockager/__init__.py
dockager/dockager_cli.py
dockager-0.0.2.dist-info/LICENSE
dockager-0.0.2.dist-info/METADATA
dockager-0.0.2.dist-info/WHEEL
dockager-0.0.2.dist-info/entry_points.txt
dockager-0.0.2.dist-info/top_level.txt
dockager-0.0.2.dist-info/RECORD
