Metadata-Version: 2.1
Name: dockager
Version: 0.0.2
Summary: Dockager
Home-page: https://github.com/dgarana/dockager
Author: David Garaña
License: UNKNOWN
Keywords: docker-compose packager
Platform: UNKNOWN
Classifier: Development Status :: 3 - Alpha
Classifier: Intended Audience :: Developers
Classifier: Topic :: Software Development :: Build Tools
Classifier: License :: OSI Approved :: MIT License
Classifier: Programming Language :: Python :: 3
Classifier: Programming Language :: Python :: 3.5
Classifier: Programming Language :: Python :: 3.6
Classifier: Programming Language :: Python :: 3.7
